debugging_benchmark
debugging_framework
