Metadata-Version: 2.1
Name: debugging-benchmark
Version: 0.0.1
Author-email: Martin Eberlein <ebermart@informatik.hu-berlin.de>, Kai Werk <werkkai@hu-berlin.de>
Project-URL: Homepage, https://github.com/martineberlein/debugging-benchmark
Project-URL: Bug Tracker, https://github.com/martineberlein/debugging-benchmark/issues
Keywords: debugging,benchmark
Classifier: Intended Audience :: Science/Research
Classifier: License :: OSI Approved :: MIT License
Classifier: Programming Language :: Python :: 3.10
Classifier: Operating System :: OS Independent
Classifier: Topic :: Scientific/Engineering
Classifier: Topic :: Software Development :: Testing
Requires-Python: >=3.10
License-File: LICENSE
Requires-Dist: fuzzingbook==1.1
Requires-Dist: jupyter
Requires-Dist: isla-solver
Requires-Dist: tests4py
Provides-Extra: dev
Requires-Dist: pytest>=7.2.0; extra == "dev"
Requires-Dist: twine; extra == "dev"
Requires-Dist: black; extra == "dev"
Requires-Dist: build; extra == "dev"
